{"result":0,"success":true,"data":[{"recommend":{"desc":"","icon":"","type":"","target_id":"","target_name":"","track_id":"cluster_v1_907@27cdjj4lyuic03507qskz"},"id":"5f320597000000000101f90e","type":"normal","timestamp":1597113751,"name":"二次元美图108","title":"二次元美图108","desc":"","inlikes":false,"likes":8,"user":{"nickname":"一路有你","images":"https://img.xiaohongshu.com/avatar/5f29f894f7c23e00017b68ba.jpg@80w_80h_90q_1e_1c_1x.jpg","red_official_verify_type":0,"userid":"5ee4544a0000000001004590"},"cursor_score":"1597131569.9490","display_title":"二次元美图108 ","images_list":[{"fileid":"2fd7a6f2-ff86-371b-9779-7dcf3472ddca","height":1440,"width":1080,"url":"http://sns-img-hw.xhscdn.com/2fd7a6f2-ff86-371b-9779-7dcf3472ddca?imageView2/2/w/540/format/jpg/q/75","original":"","url_size_large":"http://sns-img-hw.xhscdn.com/2fd7a6f2-ff86-371b-9779-7dcf3472ddca?imageView2/2/w/1080/format/webp","trace_id":"2fd7a6f2-ff86-371b-9779-7dcf3472ddca"},{"fileid":"3ca4ba0c-35c6-3f8b-af74-0e90d98a7aef","height":1440,"width":1080,"url":"","original":"","url_size_large":"http://sns-img-hw.xhscdn.com/3ca4ba0c-35c6-3f8b-af74-0e90d98a7aef?imageView2/2/w/1080/format/webp","trace_id":"3ca4ba0c-35c6-3f8b-af74-0e90d98a7aef"},{"fileid":"d2dd2970-b6ac-39d2-9c3e-2cbb54ac94a9","height":1440,"width":1080,"url":"","original":"","url_size_large":"http://sns-img-hw.xhscdn.com/d2dd2970-b6ac-39d2-9c3e-2cbb54ac94a9?imageView2/2/w/1080/format/webp","trace_id":"d2dd2970-b6ac-39d2-9c3e-2cbb54ac94a9"},{"fileid":"4b42457d-4f99-3a47-8e0c-c8a426fd4f17","height":1440,"width":1080,"url":"","original":"","url_size_large":"http://sns-img-hw.xhscdn.com/4b42457d-4f99-3a47-8e0c-c8a426fd4f17?imageView2/2/w/1080/format/webp","trace_id":"4b42457d-4f99-3a47-8e0c-c8a426fd4f17"},{"fileid":"aa6d06b2-1edf-3363-92b7-66b4fb097504","height":1440,"width":1080,"url":"","original":"","url_size_large":"http://sns-img-hw.xhscdn.com/aa6d06b2-1edf-3363-92b7-66b4fb097504?imageView2/2/w/1080/format/webp","trace_id":"aa6d06b2-1edf-3363-92b7-66b4fb097504"},{"fileid":"73284132-35e6-3efd-ad6d-c76b80fe13da","height":1440,"width":1080,"url":"","original":"","url_size_large":"http://sns-img-hw.xhscdn.com/73284132-35e6-3efd-ad6d-c76b80fe13da?imageView2/2/w/1080/format/webp","trace_id":"73284132-35e6-3efd-ad6d-c76b80fe13da"},{"fileid":"22ed567b-a79f-3fa6-aebf-df4ea61621a0","height":1440,"width":1080,"url":"","original":"","url_size_large":"http://sns-img-hw.xhscdn.com/22ed567b-a79f-3fa6-aebf-df4ea61621a0?imageView2/2/w/1080/format/webp","trace_id":"22ed567b-a79f-3fa6-aebf-df4ea61621a0"},{"fileid":"af22187c-7a39-3816-834f-4150e32f1ef9","height":1750,"width":1313,"url":"","original":"","url_size_large":"http://sns-img-hw.xhscdn.com/af22187c-7a39-3816-834f-4150e32f1ef9?imageView2/2/w/1080/format/webp","trace_id":"af22187c-7a39-3816-834f-4150e32f1ef9"},{"fileid":"c9441f0a-9ee6-388d-ba2e-65c6ec95d6d3","height":1333,"width":1000,"url":"","original":"","url_size_large":"http://sns-img-hw.xhscdn.com/c9441f0a-9ee6-388d-ba2e-65c6ec95d6d3?imageView2/2/w/1080/format/webp","trace_id":"c9441f0a-9ee6-388d-ba2e-65c6ec95d6d3"}],"model_type":"note","is_tracking":false,"debug_info":{},"is_tracking_upgrade":false,"has_music":false,"is_top_show_eco_officer_note":false},{"recommend":{"desc":"","icon":"","type":"","target_id":"","target_name":"","track_id":"dssm_dssm_v3_bn_7day@27cdjj4lyuic03507qskz","topic_id":"5db46749000000000103a004","topic_name":"二十不惑","category_id":"c00000000000000000000434","category_name":"影视片段（视频）"},"id":"5f2bd0b5000000000101dd5c","type":"video","timestamp":1596706997,"name":"寻果be，我人没了，拜拜 二十不惑","title":"寻果be，我人没了，拜拜 二十不惑","desc":"[微笑R][微笑R][微笑R]再见吧二十不惑，我气死了","inlikes":false,"likes":1278,"user":{"nickname":"大菠萝\uD83C\uDF4D是小公举\uD83D\uDC78","images":"https://img.xiaohongshu.com/avatar/5ed9bf4bf4257d00017e372e.jpg@80w_80h_90q_1e_1c_1x.jpg","red_official_verify_type":0,"userid":"55fb79ff67bc654c0d3e1a20"},"cursor_score":"1597131569.9480","display_title":"寻果be，我人没了，拜拜 二十不惑","images_list":[{"fileid":"64497e8a-9df9-3459-b497-70252b7729b5","height":1280,"width":720,"url":"http://sns-img-hw.xhscdn.com/64497e8a-9df9-3459-b497-70252b7729b5?imageView2/2/w/540/format/jpg/q/75","original":"","url_size_large":"http://sns-img-hw.xhscdn.com/64497e8a-9df9-3459-b497-70252b7729b5?imageView2/2/w/1080/format/webp","trace_id":"64497e8a-9df9-3459-b497-70252b7729b5"}],"video_info":{"id":"","height":1280,"width":720,"url":"http://sns-video-hw.xhscdn.com/e86e3cc7fe35bd667f1fb492a668da1429b80594_v1_ln","duration":59,"url_info_list":[{"desc":"h265-RedH265","url":"http://sns-video-hw.xhscdn.com/e86e3cc7fe35bd667f1fb492a668da1429b80594_v1_ln"},{"desc":"h264-RedH264","url":"http://sns-video-hw.xhscdn.com/b40a169e1fe31fe0a65939b5bb4713e57647a813_v1_ln"}],"preload_size":1048576,"played_count":0},"model_type":"note","is_tracking":false,"debug_info":{},"is_tracking_upgrade":false,"has_music":false,"is_top_show_eco_officer_note":false},{"recommend":{"desc":"","icon":"","type":"","target_id":"","target_name":"","track_id":"dssmbase_dssm_sample_new_note_dc_ns_1h@27cdjj4lyuic03507qskz","topic_id":"5f23df6000000000010034df","topic_name":"我的外母唔系人","category_id":"c00000000000000000000394","category_name":"明星娱乐资讯"},"id":"5f30f87e000000000100531f","type":"video","timestamp":1597044862,"name":"曼丽为钱做舞女","title":"曼丽为钱做舞女","desc":"","inlikes":false,"likes":263,"user":{"nickname":"花奶奶\uD83C\uDF38","images":"https://img.xiaohongshu.com/avatar/5c5e545fddab6b0001ec02d4.jpg@80w_80h_90q_1e_1c_1x.jpg","red_official_verify_type":0,"userid":"5c3609970000000006038ff0"},"cursor_score":"1597131569.9470","display_title":"曼丽为钱做舞女 ","images_list":[{"fileid":"32887047-c399-33e0-902c-38e965d57aac","height":1280,"width":720,"url":"http://sns-img-hw.xhscdn.com/32887047-c399-33e0-902c-38e965d57aac?imageView2/2/w/540/format/jpg/q/75","original":"","url_size_large":"http://sns-img-hw.xhscdn.com/32887047-c399-33e0-902c-38e965d57aac?imageView2/2/w/1080/format/webp","trace_id":"32887047-c399-33e0-902c-38e965d57aac"}],"video_info":{"id":"","height":1280,"width":720,"url":"http://sns-video-hw.xhscdn.com/ddeefcc6a658f94061d14d80b3567b5676b1c6f6_v1_ln","duration":300,"url_info_list":[{"desc":"h265-RedH265","url":"http://sns-video-hw.xhscdn.com/ddeefcc6a658f94061d14d80b3567b5676b1c6f6_v1_ln"},{"desc":"h264-RedH264","url":"http://sns-video-hw.xhscdn.com/90c8b2bd92688d829e3d9e7cdaaae4bd00c7eab8_v1_ln"}],"preload_size":1048576,"played_count":0},"model_type":"note","is_tracking":false,"debug_info":{},"is_tracking_upgrade":false,"has_music":false,"is_top_show_eco_officer_note":false},{"recommend":{"desc":"","icon":"","type":"","target_id":"","target_name":"","track_id":"itemcf_str:v2opt_0_5f0fc2a9000000000100638d@27cdjj4lyuic03507qskz","topic_id":"5e1f17f800000000010055fd","topic_name":"我家宠物真可爱","category_id":"c00000000000000000000361","category_name":"晒狗"},"id":"5f0ea4fb0000000001001c36","type":"video","timestamp":1594795259,"name":"功夫二哈来咯～","title":"功夫二哈来咯～","desc":"","inlikes":false,"likes":21788,"user":{"nickname":"宠大圣","images":"https://img.xiaohongshu.com/avatar/5e689c01acdc190001a5b550.jpg@80w_80h_90q_1e_1c_1x.jpg","red_official_verified":false,"red_official_verify_type":0,"show_red_official_verify_icon":false,"userid":"5c90bb500000000011031b3b"},"cursor_score":"1597131569.9460","display_title":"功夫二哈来咯～ ","images_list":[{"fileid":"d8a50897-3bd5-3aa5-839c-d94d7ac9ab44","height":1280,"width":720,"url":"http://sns-img-hw.xhscdn.com/d8a50897-3bd5-3aa5-839c-d94d7ac9ab44?imageView2/2/w/540/format/jpg/q/75","original":"","url_size_large":"http://sns-img-hw.xhscdn.com/d8a50897-3bd5-3aa5-839c-d94d7ac9ab44?imageView2/2/w/1080/format/webp","trace_id":"d8a50897-3bd5-3aa5-839c-d94d7ac9ab44"}],"video_info":{"id":"","height":1280,"width":720,"url":"http://sns-video-hw.xhscdn.com/3d919c1c36009fb81a4d312c602ce3d7fee2a1fc_v1","duration":36,"url_info_list":[{"desc":"h265-RedH265","url":"http://sns-video-hw.xhscdn.com/3d919c1c36009fb81a4d312c602ce3d7fee2a1fc_v1"},{"desc":"h264-RedH264","url":"http://sns-video-hw.xhscdn.com/8b2a306f5226b525db6475b767060e8db3630b63_v1"}],"preload_size":1048576,"played_count":0},"model_type":"note","is_tracking":false,"debug_info":{},"is_tracking_upgrade":false,"has_music":false,"is_top_show_eco_officer_note":false},{"recommend":{"desc":"","icon":"","type":"","target_id":"","target_name":"","track_id":"dssm_dssm_dc_multi_pool_5c14993dee05ccc9d5eef5b3@27cdjj4lyuic03507qskz","topic_id":"5a30fc8481f6d105129d36a3","topic_name":"我最爱的表情包","category_id":"5c149a73ee05ccc9d5eef5ba","category_name":"表情包"},"id":"5f156ebd0000000001006da1","type":"normal","timestamp":1595240125,"name":"\uD83D\uDCF8跟男朋友聊天～甜甜的表情包\uD83C\uDF51","title":"\uD83D\uDCF8跟男朋友聊天～甜甜的表情包\uD83C\uDF51","desc":"","inlikes":false,"likes":797,"user":{"nickname":"对你不感冒","images":"https://img.xiaohongshu.com/avatar/5f26a9780b38c9000150190b.jpg@80w_80h_90q_1e_1c_1x.jpg","red_official_verify_type":0,"userid":"5c8b8f0100000000120079e6"},"cursor_score":"1597131569.9450","display_title":"\uD83D\uDCF8跟男朋友聊天～甜甜的表情包\uD83C\uDF51","images_list":[{"fileid":"6f66c611-cd76-3286-9b7a-f2d01fb45ee6","height":480,"width":480,"url":"http://sns-img-hw.xhscdn.com/6f66c611-cd76-3286-9b7a-f2d01fb45ee6?imageView2/2/w/540/format/jpg/q/75","original":"","url_size_large":"http://sns-img-hw.xhscdn.com/6f66c611-cd76-3286-9b7a-f2d01fb45ee6?imageView2/2/w/1080/format/webp","trace_id":"6f66c611-cd76-3286-9b7a-f2d01fb45ee6"},{"fileid":"622373a6-84c6-3690-97cf-3a9bf09b34c3","height":660,"width":690,"url":"","original":"","url_size_large":"http://sns-img-hw.xhscdn.com/622373a6-84c6-3690-97cf-3a9bf09b34c3?imageView2/2/h/1080/format/webp","trace_id":"622373a6-84c6-3690-97cf-3a9bf09b34c3"},{"fileid":"e4801a5c-1a4f-3531-a151-75fe365a2481","height":240,"width":240,"url":"","original":"","url_size_large":"http://sns-img-hw.xhscdn.com/e4801a5c-1a4f-3531-a151-75fe365a2481?imageView2/2/w/1080/format/webp","trace_id":"e4801a5c-1a4f-3531-a151-75fe365a2481"},{"fileid":"55da490e-d202-36c5-9e29-e7e9fa3d006e","height":656,"width":690,"url":"","original":"","url_size_large":"http://sns-img-hw.xhscdn.com/55da490e-d202-36c5-9e29-e7e9fa3d006e?imageView2/2/h/1080/format/webp","trace_id":"55da490e-d202-36c5-9e29-e7e9fa3d006e"},{"fileid":"86fbfcfa-5be3-3987-88c7-8392a213fd83","height":440,"width":440,"url":"","original":"","url_size_large":"http://sns-img-hw.xhscdn.com/86fbfcfa-5be3-3987-88c7-8392a213fd83?imageView2/2/w/1080/format/webp","trace_id":"86fbfcfa-5be3-3987-88c7-8392a213fd83"},{"fileid":"6c03c4ed-1ef7-3c10-be67-9b037bf65047","height":638,"width":690,"url":"","original":"","url_size_large":"http://sns-img-hw.xhscdn.com/6c03c4ed-1ef7-3c10-be67-9b037bf65047?imageView2/2/h/1080/format/webp","trace_id":"6c03c4ed-1ef7-3c10-be67-9b037bf65047"},{"fileid":"ecf74c13-fee1-3a46-838f-c1a9af5aa7f6","height":684,"width":690,"url":"","original":"","url_size_large":"http://sns-img-hw.xhscdn.com/ecf74c13-fee1-3a46-838f-c1a9af5aa7f6?imageView2/2/h/1080/format/webp","trace_id":"ecf74c13-fee1-3a46-838f-c1a9af5aa7f6"},{"fileid":"72c7090b-843b-327d-b6dd-08d725df1542","height":673,"width":673,"url":"","original":"","url_size_large":"http://sns-img-hw.xhscdn.com/72c7090b-843b-327d-b6dd-08d725df1542?imageView2/2/w/1080/format/webp","trace_id":"72c7090b-843b-327d-b6dd-08d725df1542"},{"fileid":"5d864d88-0df2-3fe4-9916-908d2ff6a0aa","height":500,"width":500,"url":"","original":"","url_size_large":"http://sns-img-hw.xhscdn.com/5d864d88-0df2-3fe4-9916-908d2ff6a0aa?imageView2/2/w/1080/format/webp","trace_id":"5d864d88-0df2-3fe4-9916-908d2ff6a0aa"}],"model_type":"note","is_tracking":false,"debug_info":{},"is_tracking_upgrade":false,"has_music":false,"is_top_show_eco_officer_note":false},{"recommend":{"desc":"","icon":"","type":"","target_id":"","target_name":"","track_id":"rep_5bceca4a126ef99bc6213c18_0_iOS_19-23@27cdjj4lyuic03507qskz","topic_id":"595a327ccd30d81f6130ed8d","topic_name":"篮球","category_id":"5bcecb76126ef99bc6213c1a","category_name":"篮球赛事"},"id":"5f105ba6000000000101eb30","type":"video","timestamp":1594907558,"name":"凯里欧文","title":"凯里欧文","desc":"愿天下所有打篮球的男孩子都能被温柔以待","inlikes":false,"likes":396,"user":{"nickname":"Nick.Irving","images":"https://img.xiaohongshu.com/avatar/5f11a2a13f0af100012f8de9.jpg@80w_80h_90q_1e_1c_1x.jpg","red_official_verify_type":0,"userid":"5ef9fa8600000000010030c6"},"cursor_score":"1597131569.9440","display_title":"凯里欧文 ","images_list":[{"fileid":"a3b01bae-2267-3bfb-8b19-3534ecfb2f10","height":1088,"width":1920,"url":"http://sns-img-hw.xhscdn.com/a3b01bae-2267-3bfb-8b19-3534ecfb2f10?imageView2/2/h/540/format/jpg/q/75","original":"","url_size_large":"http://sns-img-hw.xhscdn.com/a3b01bae-2267-3bfb-8b19-3534ecfb2f10?imageView2/2/h/1080/format/webp","trace_id":"a3b01bae-2267-3bfb-8b19-3534ecfb2f10"}],"video_info":{"id":"","height":1088,"width":1920,"url":"http://sns-video-hw.xhscdn.com/c91f06df283d82692661cb399b39e0cddcb7bb08_v1","duration":26,"url_info_list":[{"desc":"h265-RedH265","url":"http://sns-video-hw.xhscdn.com/c91f06df283d82692661cb399b39e0cddcb7bb08_v1"},{"desc":"h264-RedH264","url":"http://sns-video-hw.xhscdn.com/e6fb9a75228d72d08763236ab1b2fed2aac9a527_v1"}],"preload_size":1048576,"played_count":0},"model_type":"note","is_tracking":false,"debug_info":{},"is_tracking_upgrade":false,"has_music":false,"is_top_show_eco_officer_note":false},{"recommend":{"desc":"","icon":"","type":"","target_id":"","target_name":"","track_id":"dssm_dssm_v3_bn_7day@27cdjj4lyuic03507qskz","topic_id":"59761a9f092b5b28361cd5a3","topic_name":"正在看的综艺","category_id":"c00000000000000000000436","category_name":"综艺片段"},"id":"5f2f76ff0000000001005168","type":"video","timestamp":1596946175,"name":"是不是很富有才能追女？","title":"是不是很富有才能追女？","desc":"给你选，你选哪个？[萌萌哒R]","inlikes":false,"likes":116,"user":{"nickname":"搞笑追剧君","images":"https://img.xiaohongshu.com/avatar/5f165feea736590001b1d7df.jpg@80w_80h_90q_1e_1c_1x.jpg","red_official_verify_type":0,"userid":"5c5937fa000000001b00726b"},"cursor_score":"1597131569.9430","display_title":"是不是很富有才能追女？","images_list":[{"fileid":"e3981d4c-4532-3ba0-85a9-85d9c2f8634a","height":1280,"width":720,"url":"http://sns-img-hw.xhscdn.com/e3981d4c-4532-3ba0-85a9-85d9c2f8634a?imageView2/2/w/540/format/jpg/q/75","original":"","url_size_large":"http://sns-img-hw.xhscdn.com/e3981d4c-4532-3ba0-85a9-85d9c2f8634a?imageView2/2/w/1080/format/webp","trace_id":"e3981d4c-4532-3ba0-85a9-85d9c2f8634a"}],"video_info":{"id":"","height":1280,"width":720,"url":"http://sns-video-hw.xhscdn.com/9497c54183a87d1cb8b443f22ea91d66bc7b4c5f_v1_ln","duration":82,"url_info_list":[{"desc":"h265-RedH265","url":"http://sns-video-hw.xhscdn.com/9497c54183a87d1cb8b443f22ea91d66bc7b4c5f_v1_ln"},{"desc":"h264-RedH264","url":"http://sns-video-hw.xhscdn.com/21f67d684bce25ce97102d116f3cdd691b3553a1_v1_ln"}],"preload_size":1048576,"played_count":0},"model_type":"note","is_tracking":false,"debug_info":{},"is_tracking_upgrade":false,"has_music":false,"is_top_show_eco_officer_note":false},{"recommend":{"desc":"","icon":"","type":"","target_id":"","target_name":"","track_id":"dssm_dssm_dc_multi_pool_5ab094be481d26b8ef904601@27cdjj4lyuic03507qskz","topic_id":"5be5ab9d80b72a00015399e0","topic_name":"奥迪a7","category_id":"c00000000000000000000267","category_name":"汽车介绍"},"id":"5f2e2dba000000000100501b","type":"normal","timestamp":1596861882,"name":"奥迪A7价格参考","title":"奥迪A7价格参考","desc":"奥迪A7\n20款40豪华 指导价573800 裸车优惠10个点（裸车价格517000）保险13000左右 购置税46000左右 落地价格580000左右可入\n20款45臻选 指导价612800 裸车优","inlikes":false,"likes":236,"user":{"nickname":"车界包打听","images":"https://img.xiaohongshu.com/avatar/5effecd2ccfdfe00010d5ac4.jpg@80w_80h_90q_1e_1c_1x.jpg","red_official_verify_type":0,"userid":"5b9695d36b58b74aeebc95e2"},"cursor_score":"1597131569.9420","display_title":"奥迪A7价格参考 ","images_list":[{"fileid":"e6d48c25-12d7-32a5-908a-545b8689ed68","height":1705,"width":1279,"url":"http://sns-img-hw.xhscdn.com/e6d48c25-12d7-32a5-908a-545b8689ed68?imageView2/2/w/540/format/jpg/q/75","original":"","url_size_large":"http://sns-img-hw.xhscdn.com/e6d48c25-12d7-32a5-908a-545b8689ed68?imageView2/2/w/1080/format/webp","trace_id":"e6d48c25-12d7-32a5-908a-545b8689ed68"},{"fileid":"dec1b059-9cc9-3551-b5c0-a1f297f4adba","height":1705,"width":1279,"url":"","original":"","url_size_large":"http://sns-img-hw.xhscdn.com/dec1b059-9cc9-3551-b5c0-a1f297f4adba?imageView2/2/w/1080/format/webp","trace_id":"dec1b059-9cc9-3551-b5c0-a1f297f4adba"},{"fileid":"df15b40f-d2d2-3105-85f4-705cf542bfab","height":1705,"width":1279,"url":"","original":"","url_size_large":"http://sns-img-hw.xhscdn.com/df15b40f-d2d2-3105-85f4-705cf542bfab?imageView2/2/w/1080/format/webp","trace_id":"df15b40f-d2d2-3105-85f4-705cf542bfab"},{"fileid":"e5db4686-faf1-3d9c-9d34-296202028cab","height":1705,"width":1279,"url":"","original":"","url_size_large":"http://sns-img-hw.xhscdn.com/e5db4686-faf1-3d9c-9d34-296202028cab?imageView2/2/w/1080/format/webp","trace_id":"e5db4686-faf1-3d9c-9d34-296202028cab"},{"fileid":"14634ac0-d475-3445-8eea-1c5d24d9e058","height":1705,"width":1279,"url":"","original":"","url_size_large":"http://sns-img-hw.xhscdn.com/14634ac0-d475-3445-8eea-1c5d24d9e058?imageView2/2/w/1080/format/webp","trace_id":"14634ac0-d475-3445-8eea-1c5d24d9e058"},{"fileid":"b16e9b5e-6acd-34dd-a6c6-479a571e06ff","height":1705,"width":1279,"url":"","original":"","url_size_large":"http://sns-img-hw.xhscdn.com/b16e9b5e-6acd-34dd-a6c6-479a571e06ff?imageView2/2/w/1080/format/webp","trace_id":"b16e9b5e-6acd-34dd-a6c6-479a571e06ff"},{"fileid":"93647871-11bc-3be8-b24d-b7e859022f33","height":1705,"width":1279,"url":"","original":"","url_size_large":"http://sns-img-hw.xhscdn.com/93647871-11bc-3be8-b24d-b7e859022f33?imageView2/2/w/1080/format/webp","trace_id":"93647871-11bc-3be8-b24d-b7e859022f33"},{"fileid":"fa0ab4ef-74c5-3790-82e9-b4e7958213a2","height":1079,"width":1440,"url":"","original":"","url_size_large":"http://sns-img-hw.xhscdn.com/fa0ab4ef-74c5-3790-82e9-b4e7958213a2?imageView2/2/h/1080/format/webp","trace_id":"fa0ab4ef-74c5-3790-82e9-b4e7958213a2"},{"fileid":"d7e1654e-0ef5-355c-a78c-8d1e2d307aa4","height":1079,"width":1440,"url":"","original":"","url_size_large":"http://sns-img-hw.xhscdn.com/d7e1654e-0ef5-355c-a78c-8d1e2d307aa4?imageView2/2/h/1080/format/webp","trace_id":"d7e1654e-0ef5-355c-a78c-8d1e2d307aa4"}],"model_type":"note","is_tracking":false,"debug_info":{},"is_tracking_upgrade":false,"has_music":false,"is_top_show_eco_officer_note":false},{"recommend":{"desc":"","icon":"","type":"","target_id":"","target_name":"","track_id":"dssmbase_dssm_sample_new_note_dc_ns_1h@27cdjj4lyuic03507qskz","topic_id":"59268309cd30d81ceb7a888b","topic_name":"天蝎座","category_id":"c00000000000000000000281","category_name":"星座"},"id":"5f3135aa0000000001006b60","type":"normal","timestamp":1597060522,"name":"8.10-8.16天蝎座一周运势","title":"8.10-8.16天蝎座一周运势","desc":"（塔罗运势\uD83D\uDD2E）\n爱情运：本周有伴的人在感情中会有不平衡的感觉，有时候会觉得自己的付出并没有得到回报，对感情会有很多的期待，但很难满足你。想复合的人彼此无法真心相处，还是认清两个人不合适的结果吧。\n桃","inlikes":false,"likes":13,"user":{"nickname":"藏在奶油蛋糕里\uD83C\uDF70","images":"https://img.xiaohongshu.com/avatar/5efe0653e2a1ef00010dfc77.jpg@80w_80h_90q_1e_1c_1x.jpg","red_official_verify_type":0,"userid":"5a114f1be8ac2b6117d653c2"},"cursor_score":"1597131569.9410","display_title":"8.10-8.16天蝎座一周运势","images_list":[{"fileid":"c5c3b421-e736-31e1-a116-b308089a4a6e","height":1440,"width":1080,"url":"http://sns-img-hw.xhscdn.com/c5c3b421-e736-31e1-a116-b308089a4a6e?imageView2/2/w/540/format/jpg/q/75","original":"","url_size_large":"http://sns-img-hw.xhscdn.com/c5c3b421-e736-31e1-a116-b308089a4a6e?imageView2/2/w/1080/format/webp","trace_id":"c5c3b421-e736-31e1-a116-b308089a4a6e"}],"model_type":"note","is_tracking":false,"debug_info":{},"is_tracking_upgrade":false,"has_music":false,"is_top_show_eco_officer_note":false},{"recommend":{"desc":"","icon":"","type":"","target_id":"","target_name":"","track_id":"cluster_v1_907@27cdjj4lyuic03507qskz","category_id":"5c149a5eee05ccc9d5eef5b8","category_name":"头像"},"id":"5f322b91000000000100880e","type":"normal","timestamp":1597123473,"name":"","title":"","desc":"触漫头像","inlikes":false,"likes":3,"user":{"nickname":"夏微微~[夏家]","images":"https://img.xiaohongshu.com/avatar/5f2ac3f2f7c23e00017bf075.jpg@80w_80h_90q_1e_1c_1x.jpg","red_official_verify_type":0,"userid":"5dde6b550000000001005da9"},"cursor_score":"1597131569.9400","display_title":"触漫头像 ","images_list":[{"fileid":"c1a2b798-86bd-3163-811c-cf3c24de8f0e","height":737,"width":720,"url":"http://sns-img-hw.xhscdn.com/c1a2b798-86bd-3163-811c-cf3c24de8f0e?imageView2/2/w/540/format/jpg/q/75","original":"","url_size_large":"http://sns-img-hw.xhscdn.com/c1a2b798-86bd-3163-811c-cf3c24de8f0e?imageView2/2/w/1080/format/webp","trace_id":"c1a2b798-86bd-3163-811c-cf3c24de8f0e"},{"fileid":"7d5de9af-defc-329c-8d79-63f3e68316f1","height":803,"width":720,"url":"","original":"","url_size_large":"http://sns-img-hw.xhscdn.com/7d5de9af-defc-329c-8d79-63f3e68316f1?imageView2/2/w/1080/format/webp","trace_id":"7d5de9af-defc-329c-8d79-63f3e68316f1"}],"model_type":"note","is_tracking":false,"debug_info":{},"is_tracking_upgrade":false,"has_music":false,"is_top_show_eco_officer_note":false}]}